[
    [
        "000001.json",
        {
            "epis": 1.0347106456756592,
            "recon": 1.4948102489142912e-06
        }
    ],
    [
        "000002.json",
        {
            "epis": 1.0361204147338867,
            "recon": 1.2921825600642478e-06
        }
    ],
    [
        "000003.json",
        {
            "epis": 1.0467777252197266,
            "recon": 1.1585783568079933e-06
        }
    ],
    [
        "000004.json",
        {
            "epis": 1.053350567817688,
            "recon": 1.0614313623591443e-06
        }
    ],
    [
        "000005.json",
        {
            "epis": 1.0547000169754028,
            "recon": 8.991347044684517e-07
        }
    ],
    [
        "000006.json",
        {
            "epis": 1.0605344772338867,
            "recon": 8.850440735841403e-07
        }
    ],
    [
        "000007.json",
        {
            "epis": 1.0685209035873413,
            "recon": 9.499923976363789e-07
        }
    ],
    [
        "000008.json",
        {
            "epis": 1.0663783550262451,
            "recon": 9.366854101244826e-07
        }
    ],
    [
        "000009.json",
        {
            "epis": 1.0666953325271606,
            "recon": 6.295821890489606e-07
        }
    ],
    [
        "000010.json",
        {
            "epis": 1.0656018257141113,
            "recon": 6.16352110682783e-07
        }
    ],
    [
        "000011.json",
        {
            "epis": 1.0630366802215576,
            "recon": 4.7593886165486765e-07
        }
    ],
    [
        "000012.json",
        {
            "epis": 1.0587002038955688,
            "recon": 4.5803665216226364e-07
        }
    ],
    [
        "000013.json",
        {
            "epis": 1.0517066717147827,
            "recon": 4.1948001694436243e-07
        }
    ],
    [
        "000014.json",
        {
            "epis": 1.047978401184082,
            "recon": 3.730392279521766e-07
        }
    ],
    [
        "000015.json",
        {
            "epis": 1.0425113439559937,
            "recon": 4.316856063724117e-07
        }
    ],
    [
        "000016.json",
        {
            "epis": 1.0307307243347168,
            "recon": 3.9866836232249625e-07
        }
    ],
    [
        "000017.json",
        {
            "epis": 1.0255076885223389,
            "recon": 2.853998353202769e-07
        }
    ],
    [
        "000018.json",
        {
            "epis": 1.0179760456085205,
            "recon": 4.478642097183183e-07
        }
    ],
    [
        "000019.json",
        {
            "epis": 1.0185022354125977,
            "recon": 5.322766583049088e-07
        }
    ],
    [
        "000020.json",
        {
            "epis": 1.0181982517242432,
            "recon": 3.4747378663269046e-07
        }
    ],
    [
        "000021.json",
        {
            "epis": 1.0166949033737183,
            "recon": 4.6885887172720686e-07
        }
    ],
    [
        "000022.json",
        {
            "epis": 1.0046643018722534,
            "recon": 4.312681198825885e-07
        }
    ],
    [
        "000023.json",
        {
            "epis": 0.9940352439880371,
            "recon": 3.5305390611028997e-07
        }
    ],
    [
        "000024.json",
        {
            "epis": 0.9917632341384888,
            "recon": 3.0282203056231083e-07
        }
    ],
    [
        "000025.json",
        {
            "epis": 0.986472487449646,
            "recon": 3.495314331303234e-07
        }
    ],
    [
        "000026.json",
        {
            "epis": 0.9905002117156982,
            "recon": 4.058090041780815e-07
        }
    ],
    [
        "000027.json",
        {
            "epis": 0.9898104071617126,
            "recon": 7.154992545110872e-07
        }
    ],
    [
        "000028.json",
        {
            "epis": 0.9817354083061218,
            "recon": 5.554705353461031e-07
        }
    ],
    [
        "000029.json",
        {
            "epis": 0.9691740870475769,
            "recon": 5.106520575282048e-07
        }
    ],
    [
        "000030.json",
        {
            "epis": 0.9681569933891296,
            "recon": 5.203025352784607e-07
        }
    ],
    [
        "000031.json",
        {
            "epis": 0.9600905776023865,
            "recon": 5.558163707064523e-07
        }
    ],
    [
        "000032.json",
        {
            "epis": 0.9565250277519226,
            "recon": 5.483861400534806e-07
        }
    ],
    [
        "000033.json",
        {
            "epis": 0.950994074344635,
            "recon": 6.579355726898939e-07
        }
    ],
    [
        "000034.json",
        {
            "epis": 0.9495354294776917,
            "recon": 5.188811087464273e-07
        }
    ],
    [
        "000035.json",
        {
            "epis": 0.9479742646217346,
            "recon": 4.3875206756638363e-07
        }
    ],
    [
        "000036.json",
        {
            "epis": 0.9466321468353271,
            "recon": 7.273762321347021e-07
        }
    ],
    [
        "000037.json",
        {
            "epis": 0.9456076622009277,
            "recon": 4.485815452426323e-07
        }
    ],
    [
        "000038.json",
        {
            "epis": 0.9422551989555359,
            "recon": 6.186689347487118e-07
        }
    ],
    [
        "000039.json",
        {
            "epis": 0.9469799399375916,
            "recon": 1.0653863000698038e-06
        }
    ],
    [
        "000040.json",
        {
            "epis": 0.9444008469581604,
            "recon": 1.105246269617055e-06
        }
    ],
    [
        "000041.json",
        {
            "epis": 0.941314697265625,
            "recon": 5.738717732128862e-07
        }
    ],
    [
        "000042.json",
        {
            "epis": 0.9392345547676086,
            "recon": 7.370282446572674e-07
        }
    ],
    [
        "000043.json",
        {
            "epis": 0.9328166246414185,
            "recon": 8.825348913887865e-07
        }
    ],
    [
        "000044.json",
        {
            "epis": 0.932066798210144,
            "recon": 9.264554137189407e-07
        }
    ],
    [
        "000045.json",
        {
            "epis": 0.931053102016449,
            "recon": 1.2009697911707917e-06
        }
    ],
    [
        "000046.json",
        {
            "epis": 0.930325984954834,
            "recon": 1.0965832188958302e-06
        }
    ],
    [
        "000047.json",
        {
            "epis": 0.9266195297241211,
            "recon": 8.151268957590219e-07
        }
    ],
    [
        "000048.json",
        {
            "epis": 0.9211539626121521,
            "recon": 8.747797437536065e-07
        }
    ],
    [
        "000049.json",
        {
            "epis": 0.9222349524497986,
            "recon": 7.909248438409122e-07
        }
    ],
    [
        "000050.json",
        {
            "epis": 0.9217418432235718,
            "recon": 8.146875529746467e-07
        }
    ],
    [
        "000051.json",
        {
            "epis": 0.9197900295257568,
            "recon": 1.0644580470398068e-06
        }
    ],
    [
        "000052.json",
        {
            "epis": 0.9177602529525757,
            "recon": 7.652715794392861e-07
        }
    ],
    [
        "000053.json",
        {
            "epis": 0.9150637984275818,
            "recon": 1.0238339882562286e-06
        }
    ],
    [
        "000054.json",
        {
            "epis": 0.914029061794281,
            "recon": 7.19401839432976e-07
        }
    ],
    [
        "000055.json",
        {
            "epis": 0.9154433012008667,
            "recon": 5.892511580896098e-07
        }
    ],
    [
        "000056.json",
        {
            "epis": 0.9123859405517578,
            "recon": 9.735640560393222e-07
        }
    ],
    [
        "000057.json",
        {
            "epis": 0.9124895334243774,
            "recon": 6.343024665511621e-07
        }
    ],
    [
        "000058.json",
        {
            "epis": 0.9098527431488037,
            "recon": 7.967436772560177e-07
        }
    ],
    [
        "000059.json",
        {
            "epis": 0.9086304306983948,
            "recon": 7.008488296378346e-07
        }
    ],
    [
        "000060.json",
        {
            "epis": 0.912506103515625,
            "recon": 6.359526878441102e-07
        }
    ],
    [
        "000061.json",
        {
            "epis": 0.9161347150802612,
            "recon": 6.483091965492349e-07
        }
    ],
    [
        "000062.json",
        {
            "epis": 0.9131736159324646,
            "recon": 6.204104465723503e-07
        }
    ],
    [
        "000063.json",
        {
            "epis": 0.9014981389045715,
            "recon": 7.21814558346523e-07
        }
    ],
    [
        "000064.json",
        {
            "epis": 1.0512187480926514,
            "recon": 1.083456709238817e-06
        }
    ],
    [
        "000065.json",
        {
            "epis": 1.053773045539856,
            "recon": 9.323268841399113e-07
        }
    ],
    [
        "000066.json",
        {
            "epis": 0.9083859324455261,
            "recon": 4.1982562493103615e-07
        }
    ],
    [
        "000067.json",
        {
            "epis": 0.9128842353820801,
            "recon": 5.385853683037567e-07
        }
    ],
    [
        "000068.json",
        {
            "epis": 0.9104008078575134,
            "recon": 5.473337978401105e-07
        }
    ],
    [
        "000069.json",
        {
            "epis": 0.8991283774375916,
            "recon": 6.059955808268569e-07
        }
    ],
    [
        "000070.json",
        {
            "epis": 0.8909660577774048,
            "recon": 4.875238914792135e-07
        }
    ],
    [
        "000071.json",
        {
            "epis": 0.8908566236495972,
            "recon": 5.934485898251296e-07
        }
    ],
    [
        "000072.json",
        {
            "epis": 0.8894049525260925,
            "recon": 5.350038918550126e-07
        }
    ],
    [
        "000073.json",
        {
            "epis": 0.8889263868331909,
            "recon": 4.292942037409375e-07
        }
    ],
    [
        "000074.json",
        {
            "epis": 0.8896211981773376,
            "recon": 4.0719234561947815e-07
        }
    ],
    [
        "000075.json",
        {
            "epis": 0.8880400061607361,
            "recon": 4.769290171680041e-07
        }
    ],
    [
        "000076.json",
        {
            "epis": 0.8841643333435059,
            "recon": 4.0201578599408094e-07
        }
    ],
    [
        "000077.json",
        {
            "epis": 0.8761749267578125,
            "recon": 5.431209046946606e-07
        }
    ],
    [
        "000078.json",
        {
            "epis": 0.87421053647995,
            "recon": 4.052139104260277e-07
        }
    ],
    [
        "000079.json",
        {
            "epis": 0.8648054003715515,
            "recon": 3.458295907421416e-07
        }
    ],
    [
        "000080.json",
        {
            "epis": 0.8658339381217957,
            "recon": 3.633775236266956e-07
        }
    ],
    [
        "000081.json",
        {
            "epis": 0.8651359677314758,
            "recon": 4.050200175242935e-07
        }
    ],
    [
        "000082.json",
        {
            "epis": 0.8624038696289062,
            "recon": 6.239523031581484e-07
        }
    ],
    [
        "000083.json",
        {
            "epis": 0.8627078533172607,
            "recon": 4.3976015717817063e-07
        }
    ],
    [
        "000084.json",
        {
            "epis": 0.8630204796791077,
            "recon": 5.652485697282827e-07
        }
    ],
    [
        "000085.json",
        {
            "epis": 0.8604573011398315,
            "recon": 3.45166824899934e-07
        }
    ],
    [
        "000086.json",
        {
            "epis": 0.857671320438385,
            "recon": 4.996323355044296e-07
        }
    ],
    [
        "000087.json",
        {
            "epis": 0.8556089997291565,
            "recon": 4.151604571234202e-07
        }
    ],
    [
        "000088.json",
        {
            "epis": 0.8541858196258545,
            "recon": 4.5732696207778645e-07
        }
    ],
    [
        "000089.json",
        {
            "epis": 0.8464315533638,
            "recon": 4.767466634802986e-07
        }
    ],
    [
        "000090.json",
        {
            "epis": 0.8433954119682312,
            "recon": 4.947626166540431e-07
        }
    ],
    [
        "000091.json",
        {
            "epis": 0.8397721648216248,
            "recon": 3.9381450278597185e-07
        }
    ],
    [
        "000092.json",
        {
            "epis": 0.8364344835281372,
            "recon": 4.939248015034536e-07
        }
    ],
    [
        "000093.json",
        {
            "epis": 0.8394585847854614,
            "recon": 4.3305979602337175e-07
        }
    ],
    [
        "000094.json",
        {
            "epis": 0.8357654213905334,
            "recon": 4.5382316216091567e-07
        }
    ],
    [
        "000095.json",
        {
            "epis": 0.8321599364280701,
            "recon": 3.6002106185151206e-07
        }
    ],
    [
        "000096.json",
        {
            "epis": 0.8322978615760803,
            "recon": 4.355283067525306e-07
        }
    ],
    [
        "000097.json",
        {
            "epis": 0.8269920945167542,
            "recon": 5.553416144721268e-07
        }
    ],
    [
        "000098.json",
        {
            "epis": 0.8267214894294739,
            "recon": 3.4213636013191717e-07
        }
    ],
    [
        "000099.json",
        {
            "epis": 0.8247843384742737,
            "recon": 3.798165266744036e-07
        }
    ],
    [
        "000100.json",
        {
            "epis": 0.8207061290740967,
            "recon": 3.570682451936591e-07
        }
    ],
    [
        "000101.json",
        {
            "epis": 0.8199727535247803,
            "recon": 4.075454853591509e-07
        }
    ],
    [
        "000102.json",
        {
            "epis": 0.8191255331039429,
            "recon": 4.408876748129842e-07
        }
    ],
    [
        "000103.json",
        {
            "epis": 0.8191046118736267,
            "recon": 4.2740359162962704e-07
        }
    ],
    [
        "000104.json",
        {
            "epis": 0.8183485269546509,
            "recon": 4.26011240506341e-07
        }
    ],
    [
        "000105.json",
        {
            "epis": 0.8077833652496338,
            "recon": 3.933538721412333e-07
        }
    ],
    [
        "000106.json",
        {
            "epis": 0.8107373118400574,
            "recon": 4.851317498832941e-07
        }
    ],
    [
        "000107.json",
        {
            "epis": 0.8059663772583008,
            "recon": 3.4221346822960186e-07
        }
    ],
    [
        "000108.json",
        {
            "epis": 0.8034477233886719,
            "recon": 3.812330646724149e-07
        }
    ],
    [
        "000109.json",
        {
            "epis": 0.8048234581947327,
            "recon": 4.000672220172419e-07
        }
    ],
    [
        "000110.json",
        {
            "epis": 0.8027045130729675,
            "recon": 4.690322157330229e-07
        }
    ],
    [
        "000111.json",
        {
            "epis": 0.8106961250305176,
            "recon": 4.2162511704191274e-07
        }
    ],
    [
        "000112.json",
        {
            "epis": 0.8100884556770325,
            "recon": 3.055139359275927e-07
        }
    ],
    [
        "000113.json",
        {
            "epis": 0.8090194463729858,
            "recon": 4.5728677378065186e-07
        }
    ],
    [
        "000114.json",
        {
            "epis": 0.8106468319892883,
            "recon": 4.3770771185336343e-07
        }
    ],
    [
        "000115.json",
        {
            "epis": 0.8093395233154297,
            "recon": 5.028642817705986e-07
        }
    ],
    [
        "000116.json",
        {
            "epis": 0.816836416721344,
            "recon": 3.6309120332589373e-07
        }
    ],
    [
        "000117.json",
        {
            "epis": 0.8211942911148071,
            "recon": 4.6769707751082024e-07
        }
    ],
    [
        "000118.json",
        {
            "epis": 0.820218026638031,
            "recon": 3.265615760028595e-07
        }
    ],
    [
        "000119.json",
        {
            "epis": 0.821821391582489,
            "recon": 5.467861114993866e-07
        }
    ],
    [
        "000120.json",
        {
            "epis": 0.8234107494354248,
            "recon": 3.2432521379632817e-07
        }
    ],
    [
        "000121.json",
        {
            "epis": 0.8182743191719055,
            "recon": 4.161216224929376e-07
        }
    ],
    [
        "000122.json",
        {
            "epis": 0.8138523101806641,
            "recon": 3.42510503514859e-07
        }
    ],
    [
        "000123.json",
        {
            "epis": 0.8098922967910767,
            "recon": 3.9221254155563656e-07
        }
    ],
    [
        "000124.json",
        {
            "epis": 0.8104873299598694,
            "recon": 3.5034790357713064e-07
        }
    ],
    [
        "000125.json",
        {
            "epis": 0.8083027005195618,
            "recon": 4.5166095219428826e-07
        }
    ],
    [
        "000126.json",
        {
            "epis": 0.8053004741668701,
            "recon": 3.416211029616534e-07
        }
    ],
    [
        "000127.json",
        {
            "epis": 0.8001520037651062,
            "recon": 4.4486375827546e-07
        }
    ],
    [
        "000128.json",
        {
            "epis": 0.8003724813461304,
            "recon": 3.436664712808124e-07
        }
    ],
    [
        "000129.json",
        {
            "epis": 0.8120138645172119,
            "recon": 5.62475975129928e-07
        }
    ],
    [
        "000130.json",
        {
            "epis": 0.8092849254608154,
            "recon": 3.6372827594277624e-07
        }
    ],
    [
        "000131.json",
        {
            "epis": 0.8058798909187317,
            "recon": 3.0885937007951725e-07
        }
    ],
    [
        "000132.json",
        {
            "epis": 0.8034067153930664,
            "recon": 3.6081729604120483e-07
        }
    ],
    [
        "000133.json",
        {
            "epis": 0.8059182167053223,
            "recon": 2.813700632486871e-07
        }
    ],
    [
        "000134.json",
        {
            "epis": 0.8039854764938354,
            "recon": 3.2442989095216035e-07
        }
    ],
    [
        "000135.json",
        {
            "epis": 0.8024788498878479,
            "recon": 3.055230308746104e-07
        }
    ],
    [
        "000136.json",
        {
            "epis": 0.7949864864349365,
            "recon": 3.046266385808849e-07
        }
    ],
    [
        "000137.json",
        {
            "epis": 0.7810903787612915,
            "recon": 4.676300022765645e-07
        }
    ],
    [
        "000138.json",
        {
            "epis": 0.7788465619087219,
            "recon": 3.8389137557715003e-07
        }
    ],
    [
        "000139.json",
        {
            "epis": 0.7840681672096252,
            "recon": 3.134318262709712e-07
        }
    ],
    [
        "000140.json",
        {
            "epis": 0.7799119353294373,
            "recon": 3.9874970525488607e-07
        }
    ],
    [
        "000141.json",
        {
            "epis": 0.7815564274787903,
            "recon": 3.0955214924688335e-07
        }
    ],
    [
        "000142.json",
        {
            "epis": 0.7727566957473755,
            "recon": 3.4750254940263403e-07
        }
    ],
    [
        "000143.json",
        {
            "epis": 0.7739803194999695,
            "recon": 3.0805551887169713e-07
        }
    ],
    [
        "000144.json",
        {
            "epis": 0.7722312808036804,
            "recon": 3.691149572659924e-07
        }
    ],
    [
        "000145.json",
        {
            "epis": 0.7687017321586609,
            "recon": 3.3060376836147043e-07
        }
    ],
    [
        "000146.json",
        {
            "epis": 0.7621681690216064,
            "recon": 2.941426657798729e-07
        }
    ],
    [
        "000147.json",
        {
            "epis": 0.76712965965271,
            "recon": 3.559884760306886e-07
        }
    ],
    [
        "000148.json",
        {
            "epis": 0.7621512413024902,
            "recon": 3.3299033930234145e-07
        }
    ],
    [
        "000149.json",
        {
            "epis": 0.7503082752227783,
            "recon": 3.445075833496958e-07
        }
    ],
    [
        "000150.json",
        {
            "epis": 0.7461650967597961,
            "recon": 3.019155485617375e-07
        }
    ],
    [
        "000151.json",
        {
            "epis": 0.7470736503601074,
            "recon": 4.917974365525879e-07
        }
    ],
    [
        "000152.json",
        {
            "epis": 0.7399664521217346,
            "recon": 4.082834834662208e-07
        }
    ],
    [
        "000153.json",
        {
            "epis": 0.7347279191017151,
            "recon": 4.419246408815525e-07
        }
    ],
    [
        "000154.json",
        {
            "epis": 0.7281436920166016,
            "recon": 2.818671305249154e-07
        }
    ],
    [
        "000155.json",
        {
            "epis": 0.7265941500663757,
            "recon": 3.250839029078634e-07
        }
    ],
    [
        "000156.json",
        {
            "epis": 0.7306891679763794,
            "recon": 4.4382375108398264e-07
        }
    ],
    [
        "000157.json",
        {
            "epis": 0.7318428754806519,
            "recon": 3.5490077721078706e-07
        }
    ],
    [
        "000158.json",
        {
            "epis": 0.7414951324462891,
            "recon": 3.4722782515927975e-07
        }
    ],
    [
        "000159.json",
        {
            "epis": 0.7401236295700073,
            "recon": 3.0833260211693414e-07
        }
    ],
    [
        "000160.json",
        {
            "epis": 0.7414483428001404,
            "recon": 3.455146782016527e-07
        }
    ],
    [
        "000161.json",
        {
            "epis": 0.7547834515571594,
            "recon": 4.3520122972040554e-07
        }
    ],
    [
        "000162.json",
        {
            "epis": 0.7531026601791382,
            "recon": 4.359335150638799e-07
        }
    ],
    [
        "000163.json",
        {
            "epis": 0.7520711421966553,
            "recon": 2.61304677451335e-07
        }
    ],
    [
        "000164.json",
        {
            "epis": 0.7398788928985596,
            "recon": 4.1444792486799997e-07
        }
    ],
    [
        "000165.json",
        {
            "epis": 0.7392737865447998,
            "recon": 2.7680363245963235e-07
        }
    ],
    [
        "000166.json",
        {
            "epis": 0.7403900623321533,
            "recon": 2.983251476962323e-07
        }
    ],
    [
        "000167.json",
        {
            "epis": 0.7407693862915039,
            "recon": 2.818716779984243e-07
        }
    ],
    [
        "000168.json",
        {
            "epis": 0.7415835857391357,
            "recon": 3.3353504136357515e-07
        }
    ],
    [
        "000169.json",
        {
            "epis": 0.7312110066413879,
            "recon": 2.331972552838124e-07
        }
    ],
    [
        "000170.json",
        {
            "epis": 0.7345299124717712,
            "recon": 2.441081505821785e-07
        }
    ],
    [
        "000171.json",
        {
            "epis": 0.7415161728858948,
            "recon": 3.4907492363345227e-07
        }
    ],
    [
        "000172.json",
        {
            "epis": 0.737531840801239,
            "recon": 3.949385529722349e-07
        }
    ],
    [
        "000173.json",
        {
            "epis": 0.7386524677276611,
            "recon": 2.8416397412911465e-07
        }
    ],
    [
        "000174.json",
        {
            "epis": 0.7507632374763489,
            "recon": 2.593847625576018e-07
        }
    ],
    [
        "000175.json",
        {
            "epis": 0.7533122301101685,
            "recon": 3.0508883241964213e-07
        }
    ],
    [
        "000176.json",
        {
            "epis": 0.7595522999763489,
            "recon": 2.1505790925857582e-07
        }
    ],
    [
        "000177.json",
        {
            "epis": 0.7698853611946106,
            "recon": 3.499357319469709e-07
        }
    ],
    [
        "000178.json",
        {
            "epis": 0.7775334119796753,
            "recon": 2.1773894332000054e-07
        }
    ],
    [
        "000179.json",
        {
            "epis": 0.78843092918396,
            "recon": 2.4386795871578215e-07
        }
    ],
    [
        "000180.json",
        {
            "epis": 0.7892107367515564,
            "recon": 2.4712107915547676e-07
        }
    ],
    [
        "000181.json",
        {
            "epis": 0.8125032782554626,
            "recon": 2.0017404267491656e-07
        }
    ],
    [
        "000182.json",
        {
            "epis": 0.821000874042511,
            "recon": 2.7118181833429844e-07
        }
    ],
    [
        "000183.json",
        {
            "epis": 0.8434937596321106,
            "recon": 2.3447347530236584e-07
        }
    ],
    [
        "000184.json",
        {
            "epis": 0.8545656800270081,
            "recon": 3.3544336019986076e-07
        }
    ],
    [
        "000185.json",
        {
            "epis": 0.8658846616744995,
            "recon": 3.088879338974948e-07
        }
    ],
    [
        "000186.json",
        {
            "epis": 0.8784369826316833,
            "recon": 2.51584594934684e-07
        }
    ],
    [
        "000187.json",
        {
            "epis": 0.91478431224823,
            "recon": 2.124836271377717e-07
        }
    ],
    [
        "000188.json",
        {
            "epis": 0.931486189365387,
            "recon": 2.9751726060567307e-07
        }
    ],
    [
        "000189.json",
        {
            "epis": 0.9453582763671875,
            "recon": 2.0726231753087632e-07
        }
    ],
    [
        "000190.json",
        {
            "epis": 0.8087942004203796,
            "recon": 2.30421449032292e-07
        }
    ],
    [
        "000191.json",
        {
            "epis": 0.8008689284324646,
            "recon": 2.6777775019581895e-07
        }
    ],
    [
        "000192.json",
        {
            "epis": 0.8044528365135193,
            "recon": 2.542244601499988e-07
        }
    ],
    [
        "000193.json",
        {
            "epis": 0.7993404269218445,
            "recon": 4.012026408872771e-07
        }
    ],
    [
        "000194.json",
        {
            "epis": 0.7960428595542908,
            "recon": 2.564429735230078e-07
        }
    ],
    [
        "000195.json",
        {
            "epis": 0.7900596857070923,
            "recon": 2.8231812621015706e-07
        }
    ],
    [
        "000196.json",
        {
            "epis": 0.7979803681373596,
            "recon": 3.4969980333698913e-07
        }
    ],
    [
        "000197.json",
        {
            "epis": 0.7910855412483215,
            "recon": 2.781001455787191e-07
        }
    ],
    [
        "000198.json",
        {
            "epis": 0.7910873293876648,
            "recon": 1.9942281426210684e-07
        }
    ],
    [
        "000199.json",
        {
            "epis": 0.7846032381057739,
            "recon": 2.8055106326974055e-07
        }
    ],
    [
        "000200.json",
        {
            "epis": 0.7788219451904297,
            "recon": 2.804135874612257e-07
        }
    ],
    [
        "000201.json",
        {
            "epis": 0.7754039764404297,
            "recon": 2.8636142701543577e-07
        }
    ],
    [
        "000202.json",
        {
            "epis": 0.7729710340499878,
            "recon": 2.291838683277092e-07
        }
    ],
    [
        "000203.json",
        {
            "epis": 0.7704247832298279,
            "recon": 2.744102118867886e-07
        }
    ],
    [
        "000204.json",
        {
            "epis": 0.7682043313980103,
            "recon": 2.5841936235337926e-07
        }
    ],
    [
        "000205.json",
        {
            "epis": 0.7688733339309692,
            "recon": 4.259966033259843e-07
        }
    ],
    [
        "000206.json",
        {
            "epis": 0.7665907144546509,
            "recon": 3.189831261352083e-07
        }
    ],
    [
        "000207.json",
        {
            "epis": 0.766435444355011,
            "recon": 2.5088175448217953e-07
        }
    ],
    [
        "000208.json",
        {
            "epis": 0.7702142000198364,
            "recon": 3.195952444912109e-07
        }
    ],
    [
        "000209.json",
        {
            "epis": 0.7665653824806213,
            "recon": 3.249136852900847e-07
        }
    ],
    [
        "000210.json",
        {
            "epis": 0.7697785496711731,
            "recon": 2.2001077581990103e-07
        }
    ],
    [
        "000211.json",
        {
            "epis": 0.7718796730041504,
            "recon": 3.0862773314765946e-07
        }
    ],
    [
        "000212.json",
        {
            "epis": 0.7740951180458069,
            "recon": 1.822753432634272e-07
        }
    ],
    [
        "000213.json",
        {
            "epis": 0.7751435041427612,
            "recon": 2.817384938680334e-07
        }
    ],
    [
        "000214.json",
        {
            "epis": 0.7727624773979187,
            "recon": 2.907830491949426e-07
        }
    ],
    [
        "000215.json",
        {
            "epis": 1.0659817457199097,
            "recon": 5.884253369004e-07
        }
    ],
    [
        "000216.json",
        {
            "epis": 1.0728133916854858,
            "recon": 4.400459943099122e-07
        }
    ],
    [
        "000217.json",
        {
            "epis": 1.077884316444397,
            "recon": 4.885284283773217e-07
        }
    ],
    [
        "000218.json",
        {
            "epis": 1.0770846605300903,
            "recon": 4.875657850789139e-07
        }
    ],
    [
        "000219.json",
        {
            "epis": 1.0730335712432861,
            "recon": 4.78800245673483e-07
        }
    ],
    [
        "000220.json",
        {
            "epis": 1.0673716068267822,
            "recon": 5.136137701811094e-07
        }
    ],
    [
        "000221.json",
        {
            "epis": 1.0680022239685059,
            "recon": 4.1708636899784324e-07
        }
    ],
    [
        "000222.json",
        {
            "epis": 1.0658782720565796,
            "recon": 4.0875178797250555e-07
        }
    ],
    [
        "000223.json",
        {
            "epis": 1.0625708103179932,
            "recon": 4.1475573198113125e-07
        }
    ],
    [
        "000224.json",
        {
            "epis": 1.0610135793685913,
            "recon": 4.411810152760154e-07
        }
    ],
    [
        "000225.json",
        {
            "epis": 1.0579936504364014,
            "recon": 4.432071136761806e-07
        }
    ],
    [
        "000226.json",
        {
            "epis": 1.0667656660079956,
            "recon": 4.330114222739212e-07
        }
    ],
    [
        "000227.json",
        {
            "epis": 1.0667775869369507,
            "recon": 4.827501811632828e-07
        }
    ],
    [
        "000228.json",
        {
            "epis": 1.062019944190979,
            "recon": 3.759635944788897e-07
        }
    ],
    [
        "000229.json",
        {
            "epis": 1.0576815605163574,
            "recon": 4.7177766759887163e-07
        }
    ],
    [
        "000230.json",
        {
            "epis": 1.0504448413848877,
            "recon": 3.6249153367862164e-07
        }
    ],
    [
        "000231.json",
        {
            "epis": 1.0593549013137817,
            "recon": 4.697398594544211e-07
        }
    ],
    [
        "000232.json",
        {
            "epis": 1.0602293014526367,
            "recon": 3.7008970821261755e-07
        }
    ],
    [
        "000233.json",
        {
            "epis": 1.053674340248108,
            "recon": 4.1081864310399396e-07
        }
    ],
    [
        "000234.json",
        {
            "epis": 1.0483759641647339,
            "recon": 4.860171998188889e-07
        }
    ],
    [
        "000235.json",
        {
            "epis": 1.034397006034851,
            "recon": 4.198839178570779e-07
        }
    ],
    [
        "000236.json",
        {
            "epis": 1.040419340133667,
            "recon": 4.1924090510292444e-07
        }
    ],
    [
        "000237.json",
        {
            "epis": 1.0411186218261719,
            "recon": 3.407575661640294e-07
        }
    ],
    [
        "000238.json",
        {
            "epis": 1.0464001893997192,
            "recon": 3.750147641312651e-07
        }
    ],
    [
        "000239.json",
        {
            "epis": 1.0369184017181396,
            "recon": 4.09737850759484e-07
        }
    ],
    [
        "000240.json",
        {
            "epis": 1.0453230142593384,
            "recon": 3.756963167234062e-07
        }
    ],
    [
        "000241.json",
        {
            "epis": 1.0445539951324463,
            "recon": 4.67587113917034e-07
        }
    ],
    [
        "000242.json",
        {
            "epis": 1.0425573587417603,
            "recon": 4.141816987157654e-07
        }
    ],
    [
        "000243.json",
        {
            "epis": 1.040146827697754,
            "recon": 4.4069935256629833e-07
        }
    ],
    [
        "000244.json",
        {
            "epis": 1.0301551818847656,
            "recon": 4.126859209918621e-07
        }
    ],
    [
        "000245.json",
        {
            "epis": 1.0335856676101685,
            "recon": 4.6436761635959556e-07
        }
    ],
    [
        "000246.json",
        {
            "epis": 1.0397725105285645,
            "recon": 4.3086262735414493e-07
        }
    ],
    [
        "000247.json",
        {
            "epis": 1.0399802923202515,
            "recon": 4.974353942088783e-07
        }
    ],
    [
        "000248.json",
        {
            "epis": 1.0368587970733643,
            "recon": 4.5382125790638383e-07
        }
    ],
    [
        "000249.json",
        {
            "epis": 1.0486135482788086,
            "recon": 3.988960486367432e-07
        }
    ]
]